{
  "collectionName": "components_plugins_liens",
  "info": {
    "displayName": "Lien",
    "icon": "share",
    "description": ""
  },
  "options": {},
  "attributes": {
    "Titre": {
      "type": "string",
      "required": true
    },
    "Url": {
      "type": "string",
      "required": true
    },
    "Description": {
      "type": "string"
    },
    "Cible": {
      "type": "enumeration",
      "enum": [
        "_blank",
        "_self"
      ]
    },
    "Alias": {
      "type": "string",
      "required": true
    }
  }
}
